{
 "updated": "2026-07-10T08:51:32.286Z",
 "usdtry": 46.97999954223633,
 "rows": [
  {
   "name": "TUPRS",
   "sym": "TUPRS.IS",
   "tip": "BIST",
   "s1": 40,
   "s4": 60,
   "common": 52,
   "sig": "İZLE",
   "secondBuy": false,
   "warrant": false,
   "risk": 82,
   "rsi": 69,
   "adx": 49,
   "relVol": 0.19,
   "close": 266.25
  },
  {
   "name": "KONTR",
   "sym": "KONTR.IS",
   "tip": "BIST",
   "s1": 60,
   "s4": 40,
   "common": 48,
   "sig": "—",
   "secondBuy": false,
   "warrant": false,
   "risk": 100,
   "rsi": 92,
   "adx": 62,
   "relVol": null,
   "close": 5.38
  },
  {
   "name": "EREGL",
   "sym": "EREGL.IS",
   "tip": "BIST",
   "s1": 50,
   "s4": 45,
   "common": 47,
   "sig": "—",
   "secondBuy": false,
   "warrant": false,
   "risk": 28,
   "rsi": 58,
   "adx": 26,
   "relVol": 0.12,
   "close": 40.78
  },
  {
   "name": "ASTOR",
   "sym": "ASTOR.IS",
   "tip": "BIST",
   "s1": 20,
   "s4": 50,
   "common": 38,
   "sig": "—",
   "secondBuy": false,
   "warrant": false,
   "risk": 71,
   "rsi": 56,
   "adx": 18,
   "relVol": 0.08,
   "close": 318.5
  },
  {
   "name": "KCHOL",
   "sym": "KCHOL.IS",
   "tip": "BIST",
   "s1": 50,
   "s4": 30,
   "common": 38,
   "sig": "—",
   "secondBuy": false,
   "warrant": false,
   "risk": 26,
   "rsi": 65,
   "adx": 26,
   "relVol": 0.22,
   "close": 189.8
  },
  {
   "name": "Altın (Ons)",
   "sym": "GC=F",
   "tip": "Emtia",
   "s1": 30,
   "s4": 40,
   "common": 36,
   "sig": "—",
   "secondBuy": false,
   "warrant": false,
   "risk": 10,
   "rsi": 43,
   "adx": 16,
   "relVol": 0.52,
   "close": 4110.2,
   "gram": 6208.21
  },
  {
   "name": "WTI",
   "sym": "CL=F",
   "tip": "Emtia",
   "s1": 0,
   "s4": 60,
   "common": 36,
   "sig": "—",
   "secondBuy": false,
   "warrant": false,
   "risk": 34,
   "rsi": 44,
   "adx": 24,
   "relVol": 0.69,
   "close": 71.98
  },
  {
   "name": "FROTO",
   "sym": "FROTO.IS",
   "tip": "BIST",
   "s1": 20,
   "s4": 45,
   "common": 35,
   "sig": "—",
   "secondBuy": false,
   "warrant": false,
   "risk": 46,
   "rsi": 45,
   "adx": 22,
   "relVol": 0.09,
   "close": 81.2
  },
  {
   "name": "ENKAI",
   "sym": "ENKAI.IS",
   "tip": "BIST",
   "s1": 30,
   "s4": 35,
   "common": 33,
   "sig": "—",
   "secondBuy": false,
   "warrant": false,
   "risk": 31,
   "rsi": 47,
   "adx": 26,
   "relVol": 0.07,
   "close": 89.65
  },
  {
   "name": "HEKTS",
   "sym": "HEKTS.IS",
   "tip": "BIST",
   "s1": 30,
   "s4": 35,
   "common": 33,
   "sig": "—",
   "secondBuy": false,
   "warrant": false,
   "risk": 100,
   "rsi": 52,
   "adx": 31,
   "relVol": 0.09,
   "close": 3.08
  },
  {
   "name": "KRDMD",
   "sym": "KRDMD.IS",
   "tip": "BIST",
   "s1": 30,
   "s4": 35,
   "common": 33,
   "sig": "—",
   "secondBuy": false,
   "warrant": false,
   "risk": 62,
   "rsi": 49,
   "adx": 27,
   "relVol": 0.13,
   "close": 37.02
  },
  {
   "name": "SAHOL",
   "sym": "SAHOL.IS",
   "tip": "BIST",
   "s1": 30,
   "s4": 35,
   "common": 33,
   "sig": "—",
   "secondBuy": false,
   "warrant": false,
   "risk": 53,
   "rsi": 47,
   "adx": 33,
   "relVol": 0.23,
   "close": 90.8
  },
  {
   "name": "SASA",
   "sym": "SASA.IS",
   "tip": "BIST",
   "s1": 50,
   "s4": 20,
   "common": 32,
   "sig": "—",
   "secondBuy": false,
   "warrant": false,
   "risk": 58,
   "rsi": 64,
   "adx": 36,
   "relVol": 0.09,
   "close": 2.39
  },
  {
   "name": "Brent",
   "sym": "BZ=F",
   "tip": "Emtia",
   "s1": 0,
   "s4": 50,
   "common": 30,
   "sig": "—",
   "secondBuy": false,
   "warrant": false,
   "risk": 37,
   "rsi": 44,
   "adx": 20,
   "relVol": 1.18,
   "close": 76.25
  },
  {
   "name": "ARCLK",
   "sym": "ARCLK.IS",
   "tip": "BIST",
   "s1": 20,
   "s4": 35,
   "common": 29,
   "sig": "—",
   "secondBuy": false,
   "warrant": false,
   "risk": 32,
   "rsi": 53,
   "adx": 24,
   "relVol": 0.06,
   "close": 97.8
  },
  {
   "name": "OYAKC",
   "sym": "OYAKC.IS",
   "tip": "BIST",
   "s1": 20,
   "s4": 35,
   "common": 29,
   "sig": "—",
   "secondBuy": false,
   "warrant": false,
   "risk": 37,
   "rsi": 48,
   "adx": 24,
   "relVol": 0.11,
   "close": 20.14
  },
  {
   "name": "TCELL",
   "sym": "TCELL.IS",
   "tip": "BIST",
   "s1": 20,
   "s4": 35,
   "common": 29,
   "sig": "—",
   "secondBuy": false,
   "warrant": false,
   "risk": 37,
   "rsi": 46,
   "adx": 15,
   "relVol": 0.04,
   "close": 105.5
  },
  {
   "name": "THYAO",
   "sym": "THYAO.IS",
   "tip": "BIST",
   "s1": 10,
   "s4": 40,
   "common": 28,
   "sig": "—",
   "secondBuy": false,
   "warrant": false,
   "risk": 38,
   "rsi": 52,
   "adx": 27,
   "relVol": 0.07,
   "close": 339.5
  },
  {
   "name": "PETKM",
   "sym": "PETKM.IS",
   "tip": "BIST",
   "s1": 50,
   "s4": 10,
   "common": 26,
   "sig": "—",
   "secondBuy": false,
   "warrant": false,
   "risk": 18,
   "rsi": 58,
   "adx": 25,
   "relVol": 0.08,
   "close": 19.48
  },
  {
   "name": "ULKER",
   "sym": "ULKER.IS",
   "tip": "BIST",
   "s1": 20,
   "s4": 30,
   "common": 26,
   "sig": "—",
   "secondBuy": false,
   "warrant": false,
   "risk": 53,
   "rsi": 52,
   "adx": 19,
   "relVol": 0.18,
   "close": 97.9
  },
  {
   "name": "AKBNK",
   "sym": "AKBNK.IS",
   "tip": "BIST",
   "s1": 30,
   "s4": 20,
   "common": 24,
   "sig": "—",
   "secondBuy": false,
   "warrant": false,
   "risk": 60,
   "rsi": 29,
   "adx": 42,
   "relVol": 0.09,
   "close": 70.3
  },
  {
   "name": "GUBRF",
   "sym": "GUBRF.IS",
   "tip": "BIST",
   "s1": 30,
   "s4": 20,
   "common": 24,
   "sig": "—",
   "secondBuy": false,
   "warrant": false,
   "risk": 57,
   "rsi": 54,
   "adx": 28,
   "relVol": 0.37,
   "close": 446.5
  },
  {
   "name": "Gümüş",
   "sym": "SI=F",
   "tip": "Emtia",
   "s1": 30,
   "s4": 20,
   "common": 24,
   "sig": "—",
   "secondBuy": false,
   "warrant": false,
   "risk": 21,
   "rsi": 45,
   "adx": 22,
   "relVol": 0.58,
   "close": 59.99
  },
  {
   "name": "BIMAS",
   "sym": "BIMAS.IS",
   "tip": "BIST",
   "s1": 40,
   "s4": 10,
   "common": 22,
   "sig": "—",
   "secondBuy": false,
   "warrant": false,
   "risk": 26,
   "rsi": 52,
   "adx": 22,
   "relVol": 0.08,
   "close": 371
  },
  {
   "name": "BRSAN",
   "sym": "BRSAN.IS",
   "tip": "BIST",
   "s1": 30,
   "s4": 15,
   "common": 21,
   "sig": "—",
   "secondBuy": false,
   "warrant": false,
   "risk": 65,
   "rsi": 47,
   "adx": 34,
   "relVol": 0.05,
   "close": 536.5
  },
  {
   "name": "ASELS",
   "sym": "ASELS.IS",
   "tip": "BIST",
   "s1": 20,
   "s4": 20,
   "common": 20,
   "sig": "—",
   "secondBuy": false,
   "warrant": false,
   "risk": 44,
   "rsi": 49,
   "adx": 35,
   "relVol": 0.2,
   "close": 373.75
  },
  {
   "name": "EKGYO",
   "sym": "EKGYO.IS",
   "tip": "BIST",
   "s1": 20,
   "s4": 20,
   "common": 20,
   "sig": "—",
   "secondBuy": false,
   "warrant": false,
   "risk": 30,
   "rsi": 52,
   "adx": 18,
   "relVol": 0.05,
   "close": 20.66
  },
  {
   "name": "PGSUS",
   "sym": "PGSUS.IS",
   "tip": "BIST",
   "s1": 30,
   "s4": 10,
   "common": 18,
   "sig": "—",
   "secondBuy": false,
   "warrant": false,
   "risk": 41,
   "rsi": 49,
   "adx": 30,
   "relVol": 0.09,
   "close": 168.9
  },
  {
   "name": "SISE",
   "sym": "SISE.IS",
   "tip": "BIST",
   "s1": 30,
   "s4": 10,
   "common": 18,
   "sig": "—",
   "secondBuy": false,
   "warrant": false,
   "risk": 39,
   "rsi": 55,
   "adx": 23,
   "relVol": 0.07,
   "close": 42.96
  },
  {
   "name": "YKBNK",
   "sym": "YKBNK.IS",
   "tip": "BIST",
   "s1": 30,
   "s4": 10,
   "common": 18,
   "sig": "—",
   "secondBuy": false,
   "warrant": false,
   "risk": 74,
   "rsi": 32,
   "adx": 37,
   "relVol": 0.19,
   "close": 35.88
  },
  {
   "name": "GARAN",
   "sym": "GARAN.IS",
   "tip": "BIST",
   "s1": 20,
   "s4": 10,
   "common": 14,
   "sig": "—",
   "secondBuy": false,
   "warrant": false,
   "risk": 41,
   "rsi": 47,
   "adx": 22,
   "relVol": 0.06,
   "close": 131.3
  },
  {
   "name": "ISCTR",
   "sym": "ISCTR.IS",
   "tip": "BIST",
   "s1": 20,
   "s4": 10,
   "common": 14,
   "sig": "—",
   "secondBuy": false,
   "warrant": false,
   "risk": 43,
   "rsi": 42,
   "adx": 18,
   "relVol": 0.11,
   "close": 14.01
  },
  {
   "name": "TOASO",
   "sym": "TOASO.IS",
   "tip": "BIST",
   "s1": 20,
   "s4": 0,
   "common": 8,
   "sig": "—",
   "secondBuy": false,
   "warrant": false,
   "risk": 46,
   "rsi": 51,
   "adx": 14,
   "relVol": 0.06,
   "close": 298
  },
  {
   "name": "KOZAL",
   "sym": "KOZAL.IS",
   "tip": "BIST",
   "err": "HTTP 404"
  }
 ]
}